app/__init__.py
DetectorColor-0.1.dist-info/LICENSE.txt
DetectorColor-0.1.dist-info/METADATA
DetectorColor-0.1.dist-info/WHEEL
DetectorColor-0.1.dist-info/top_level.txt
DetectorColor-0.1.dist-info/RECORD
